tf_yarn/__init__.py
tf_yarn/_criteo.py
tf_yarn/_env.py
tf_yarn/_internal.py
tf_yarn/_task_commons.py
tf_yarn/client.py
tf_yarn/cluster.py
tf_yarn/constants.py
tf_yarn/default.log.conf
tf_yarn/evaluator_metrics.py
tf_yarn/event.py
tf_yarn/experiment.py
tf_yarn/keras_experiment.py
tf_yarn/metrics.py
tf_yarn/mlflow.py
tf_yarn/packaging.py
tf_yarn/tensorboard.py
tf_yarn/topologies.py
tf_yarn/bin/__init__.py
tf_yarn/bin/check_hadoop_env.py
tf_yarn/tasks/__init__.py
tf_yarn/tasks/_independent_workers_task.py
tf_yarn/tasks/_tensorboard_task.py
tf_yarn/tasks/evaluator_task.py
tf_yarn/tasks/gloo_allred_task.py
tf_yarn/tasks/logging.py
tf_yarn_gpu-0.6.3.dist-info/LICENSE
tf_yarn_gpu-0.6.3.dist-info/METADATA
tf_yarn_gpu-0.6.3.dist-info/WHEEL
tf_yarn_gpu-0.6.3.dist-info/entry_points.txt
tf_yarn_gpu-0.6.3.dist-info/top_level.txt
tf_yarn_gpu-0.6.3.dist-info/RECORD
