Metadata-Version: 2.1
Name: tf-yarn-gpu
Version: 0.6.3
Summary: Distributed TensorFlow on a YARN cluster with Gpu support
Home-page: https://github.com/criteo/tf-yarn
Maintainer: Criteo
Maintainer-email: github@criteo.com
License: UNKNOWN
Keywords: tensorflow yarn gpu
Platform: UNKNOWN
Classifier: Development Status :: 4 - Beta
Classifier: Intended Audience :: Developers
Classifier: Intended Audience :: Science/Research
Classifier: Operating System :: POSIX :: Linux
Classifier: Environment :: Console
Classifier: License :: OSI Approved :: Apache Software License
Classifier: Programming Language :: Python :: 3
Classifier: Programming Language :: Python :: 3.6
Classifier: Programming Language :: Python :: 3.7
Classifier: Topic :: Software Development :: Libraries
Requires-Python: >=3.6
License-File: LICENSE
Requires-Dist: cluster-pack
Requires-Dist: skein (<0.9,>=0.8)
Requires-Dist: tensorflow-gpu (<=2.4.1,>=1.15)
